PyIFS/InfFS.py
PyIFS/__init__.py
PyIFS-0.0.3.dist-info/LICENSE
PyIFS-0.0.3.dist-info/METADATA
PyIFS-0.0.3.dist-info/WHEEL
PyIFS-0.0.3.dist-info/top_level.txt
PyIFS-0.0.3.dist-info/RECORD
