Metadata-Version: 2.1
Name: PyIFS
Version: 0.0.3
Summary: A python3 package for infinite feature selection
Home-page: https://https://github.com/InfOmics/PyIFS
Author: nightwnvol
Author-email: notte_94@hotmail.it
License: UNKNOWN
Platform: UNKNOWN
Classifier: Programming Language :: Python :: 3
Classifier: License :: OSI Approved :: MIT License
Classifier: Operating System :: OS Independent
Requires-Python: >=3.6
Requires-Dist: numpy
